{
  "collectionName": "components_general_contacts",
  "info": {
    "displayName": "contacts",
    "icon": "address-book",
    "description": ""
  },
  "options": {},
  "attributes": {
    "addressFirstLine": {
      "type": "string"
    },
    "address": {
      "type": "text"
    },
    "openingHoursPage": {
      "type": "relation",
      "relation": "oneToOne",
      "target": "api::page.page"
    },
    "contact": {
      "type": "relation",
      "relation": "oneToOne",
      "target": "api::contact.contact"
    },
    "contactsPage": {
      "type": "relation",
      "relation": "oneToOne",
      "target": "api::page.page"
    },
    "latitude": {
      "type": "string"
    },
    "longitude": {
      "type": "string"
    },
    "navigateToLink": {
      "type": "string"
    }
  }
}
